configpile/__init__.py
configpile/arg.py
configpile/calculator.py
configpile/collector.py
configpile/config.py
configpile/enums.py
configpile/handlers.py
configpile/parsers.py
configpile/processor.py
configpile/py.typed
configpile/userr.py
configpile/util.py
configpile-10.1.3.dist-info/LICENSE
configpile-10.1.3.dist-info/WHEEL
configpile-10.1.3.dist-info/METADATA
configpile-10.1.3.dist-info/RECORD
