Metadata-Version: 2.1
Name: configpile
Version: 10.1.3
Summary: Configuration from command line parameters, configuration files and environment variables
Home-page: https://github.com/denisrosset/configpile.git
License: MIT
Author: Denis Rosset
Author-email: physics@denisrosset.com
Requires-Python: >=3.8,<4.0
Classifier: License :: OSI Approved :: MIT License
Classifier: Programming Language :: Python :: 3
Classifier: Programming Language :: Python :: 3.8
Classifier: Programming Language :: Python :: 3.9
Classifier: Programming Language :: Python :: 3.10
Classifier: Programming Language :: Python :: 3.11
Provides-Extra: docs
Provides-Extra: parsy
Provides-Extra: rich
Requires-Dist: class-doc (>=0.2.6,<0.3.0)
Requires-Dist: myst-nb (>=0.13.2,<0.14.0); extra == "docs"
Requires-Dist: parsy (>=1.4.0,<2.0.0); extra == "parsy"
Requires-Dist: rich (>=11.2.0,<12.0.0); extra == "rich"
Requires-Dist: sphinx (==4.3.2); extra == "docs"
Requires-Dist: sphinx-argparse (>=0.3.1,<0.4.0); extra == "docs"
Requires-Dist: sphinx-autodoc-typehints (>=1.17.0,<2.0.0); extra == "docs"
Requires-Dist: sphinx-book-theme (>=0.2.0,<0.3.0); extra == "docs"
Requires-Dist: sphinxcontrib-programoutput (>=0.17,<0.18); extra == "docs"
Requires-Dist: typing-extensions (>=4.1.1,<5.0.0)
Project-URL: Repository, https://github.com/denisrosset/configpile.git
